<Properties StartupConfiguration="{BCA4B549-D349-4432-AD6A-E42DC8FB0C13}|Default">
  <MonoDevelop.Ide.DebuggingService.PinnedWatches />
  <MonoDevelop.Ide.Workbench>
    <Pads>
      <Pad Id="ProjectPad">
        <State name="__root__">
          <Node name="training" expanded="True">
            <Node name="training" expanded="True" selected="True">
              <Node name="Controllers" expanded="True" />
              <Node name="Model" expanded="True" />
              <Node name="Properties" expanded="True" />
              <Node name="appsettings.json" expanded="True" />
            </Node>
          </Node>
        </State>
      </Pad>
    </Pads>
  </MonoDevelop.Ide.Workbench>
  <MultiItemStartupConfigurations />
  <MonoDevelop.Ide.ItemProperties.training PreferredExecutionTarget="/Applications/Google Chrome.app" />
  <MonoDevelop.Ide.Workspace ActiveConfiguration="Debug" />
  <MonoDevelop.Ide.ItemProperties.sample FirstBuild="True" />
  <MonoDevelop.Ide.DebuggingService.Breakpoints />
</Properties>